{
  "timestamp": "2026-07-15T12:59:04.679Z",
  "updateTime": "2026/07/15 21:59:04",
  "source": "MoneyBox (明洞換匯所聯盟)",
  "sourceUrl": "https://moneybox-exchange.com/zh-CHT/exchange",
  "apiUrl": "https://cems.moneybox.or.kr/api/cmd.php?cmd=C011&key=U1D8I4W7V6S1L3U4F3I4",
  "base": "KRW",
  "rates": {
    "USD": {
      "currency": "USD",
      "base": 1490.6,
      "buy": 1495,
      "sell": 1486,
      "spbuy": 1516.68,
      "spsell": 1464.52
    },
    "JPY": {
      "currency": "JPY",
      "base": 918.9,
      "buy": 925,
      "sell": 917,
      "spbuy": 934.98,
      "spsell": 902.82
    },
    "CNY": {
      "currency": "CNY",
      "base": 220.11,
      "buy": 219,
      "sell": 218.3,
      "spbuy": 231.11,
      "spsell": 209.11
    },
    "EUR": {
      "currency": "EUR",
      "base": 1703.31,
      "buy": 1705,
      "sell": 1690,
      "spbuy": 1737.2,
      "spsell": 1669.42
    },
    "HKD": {
      "currency": "HKD",
      "base": 190.16,
      "buy": 191,
      "sell": 189,
      "spbuy": 193.9,
      "spsell": 186.42
    },
    "TWD": {
      "currency": "TWD",
      "base": 46.32,
      "buy": 45.1,
      "sell": 45,
      "spbuy": 52.38,
      "spsell": 41.69
    },
    "SGD": {
      "currency": "SGD",
      "base": 1154.65,
      "buy": 1160,
      "sell": 1145,
      "spbuy": 1177.62,
      "spsell": 1131.68
    },
    "THB": {
      "currency": "THB",
      "base": 44.38,
      "buy": 46.5,
      "sell": 45,
      "spbuy": 46.59,
      "spsell": 41.72
    },
    "PHP": {
      "currency": "PHP",
      "base": 24.17,
      "buy": 25.3,
      "sell": 24.6,
      "spbuy": 26.58,
      "spsell": 22.19
    },
    "MYR": {
      "currency": "MYR",
      "base": 365.52,
      "buy": 370,
      "sell": 355,
      "spbuy": 392.56,
      "spsell": 338.48
    },
    "IDR": {
      "currency": "IDR",
      "base": 8.27,
      "buy": 9,
      "sell": 8.5,
      "spbuy": 9.09,
      "spsell": 7.45
    },
    "VND": {
      "currency": "VND",
      "base": 5.69,
      "buy": 6,
      "sell": 5.7,
      "spbuy": 6.36,
      "spsell": 5.02
    },
    "AUD": {
      "currency": "AUD",
      "base": 1042.53,
      "buy": 1055,
      "sell": 1030,
      "spbuy": 1063.06,
      "spsell": 1022
    },
    "GBP": {
      "currency": "GBP",
      "base": 2001.21,
      "buy": 2020,
      "sell": 1975,
      "spbuy": 2040.63,
      "spsell": 1961.79
    },
    "RUB": {
      "currency": "RUB",
      "base": 19.09,
      "buy": 18.8,
      "sell": 16,
      "spbuy": 20.9,
      "spsell": 15.75
    },
    "CHF": {
      "currency": "CHF",
      "base": 1841.95,
      "buy": 1854.648,
      "sell": 1810,
      "spbuy": 1878.23,
      "spsell": 1805.67
    },
    "CAD": {
      "currency": "CAD",
      "base": 1060.51,
      "buy": 1065,
      "sell": 1050,
      "spbuy": 1081.4,
      "spsell": 1039.62
    },
    "NZD": {
      "currency": "NZD",
      "base": 869.09,
      "buy": 880,
      "sell": 850,
      "spbuy": 886.21,
      "spsell": 851.97
    },
    "AED": {
      "currency": "AED",
      "base": 405.83,
      "buy": 414.758,
      "sell": 385,
      "spbuy": 428.15,
      "spsell": 377.83
    },
    "GFT": {
      "currency": "GFT",
      "base": 1,
      "buy": 1,
      "sell": 0.95,
      "spbuy": 1,
      "spsell": 1
    }
  }
}