{
  "timestamp": "2026-07-23T09:40:49.020Z",
  "updateTime": "2026/07/23 18:40:49",
  "source": "MoneyBox (明洞換匯所聯盟)",
  "sourceUrl": "https://moneybox-exchange.com/zh-CHT/exchange",
  "apiUrl": "https://cems.moneybox.or.kr/api/cmd.php?cmd=C011&key=U1D8I4W7V6S1L3U4F3I4",
  "base": "KRW",
  "rates": {
    "USD": {
      "currency": "USD",
      "base": 1469.7,
      "buy": 1474,
      "sell": 1465,
      "spbuy": 1495.41,
      "spsell": 1443.99
    },
    "JPY": {
      "currency": "JPY",
      "base": 899.67,
      "buy": 905,
      "sell": 898,
      "spbuy": 915.41,
      "spsell": 883.93
    },
    "CNY": {
      "currency": "CNY",
      "base": 217.09,
      "buy": 216.3,
      "sell": 215,
      "spbuy": 227.94,
      "spsell": 206.24
    },
    "EUR": {
      "currency": "EUR",
      "base": 1677.07,
      "buy": 1675,
      "sell": 1660,
      "spbuy": 1710.44,
      "spsell": 1643.7
    },
    "HKD": {
      "currency": "HKD",
      "base": 187.45,
      "buy": 187.5,
      "sell": 186,
      "spbuy": 191.14,
      "spsell": 183.76
    },
    "TWD": {
      "currency": "TWD",
      "base": 45.52,
      "buy": 44.1,
      "sell": 43.8,
      "spbuy": 51.48,
      "spsell": 40.97
    },
    "SGD": {
      "currency": "SGD",
      "base": 1138.82,
      "buy": 1145,
      "sell": 1130,
      "spbuy": 1161.48,
      "spsell": 1116.16
    },
    "THB": {
      "currency": "THB",
      "base": 43.48,
      "buy": 45.5,
      "sell": 44.5,
      "spbuy": 45.65,
      "spsell": 40.88
    },
    "PHP": {
      "currency": "PHP",
      "base": 23.81,
      "buy": 25,
      "sell": 24.3,
      "spbuy": 26.19,
      "spsell": 21.86
    },
    "MYR": {
      "currency": "MYR",
      "base": 359.47,
      "buy": 365,
      "sell": 355,
      "spbuy": 386.07,
      "spsell": 332.87
    },
    "IDR": {
      "currency": "IDR",
      "base": 8.23,
      "buy": 10,
      "sell": 8.4,
      "spbuy": 9.05,
      "spsell": 7.41
    },
    "VND": {
      "currency": "VND",
      "base": 5.6,
      "buy": 5.85,
      "sell": 5.6,
      "spbuy": 6.26,
      "spsell": 4.94
    },
    "AUD": {
      "currency": "AUD",
      "base": 1028.79,
      "buy": 1030,
      "sell": 1020,
      "spbuy": 1049.05,
      "spsell": 1008.53
    },
    "GBP": {
      "currency": "GBP",
      "base": 1965.65,
      "buy": 1985,
      "sell": 1945,
      "spbuy": 2004.37,
      "spsell": 1926.93
    },
    "RUB": {
      "currency": "RUB",
      "base": 18.7,
      "buy": 18.4,
      "sell": 16,
      "spbuy": 20.47,
      "spsell": 15.43
    },
    "CHF": {
      "currency": "CHF",
      "base": 1803.64,
      "buy": 1810,
      "sell": 1790,
      "spbuy": 1839.17,
      "spsell": 1768.11
    },
    "CAD": {
      "currency": "CAD",
      "base": 1043.86,
      "buy": 1060,
      "sell": 1030,
      "spbuy": 1064.42,
      "spsell": 1023.3
    },
    "NZD": {
      "currency": "NZD",
      "base": 851.91,
      "buy": 880,
      "sell": 850,
      "spbuy": 868.69,
      "spsell": 835.13
    },
    "AED": {
      "currency": "AED",
      "base": 400.17,
      "buy": 408.97,
      "sell": 375,
      "spbuy": 422.17,
      "spsell": 372.56
    },
    "GFT": {
      "currency": "GFT",
      "base": 1,
      "buy": 1,
      "sell": 0.95,
      "spbuy": 1,
      "spsell": 1
    }
  }
}