{
  "timestamp": "2026-04-22T01:08:59.122Z",
  "updateTime": "2026/04/22 10:08:59",
  "source": "MoneyBox (明洞換匯所聯盟)",
  "sourceUrl": "https://moneybox-exchange.com/zh-CHT/exchange",
  "apiUrl": "https://cems.moneybox.or.kr/api/cmd.php?cmd=C011&key=U1D8I4W7V6S1L3U4F3I4",
  "base": "KRW",
  "rates": {
    "USD": {
      "currency": "USD",
      "base": 1477.9,
      "buy": 1474,
      "sell": 1470,
      "spbuy": 1503.76,
      "spsell": 1452.04
    },
    "JPY": {
      "currency": "JPY",
      "base": 927.78,
      "buy": 930,
      "sell": 923,
      "spbuy": 944.01,
      "spsell": 911.55
    },
    "CNY": {
      "currency": "CNY",
      "base": 216.53,
      "buy": 214,
      "sell": 212.5,
      "spbuy": 227.35,
      "spsell": 205.71
    },
    "EUR": {
      "currency": "EUR",
      "base": 1735.5,
      "buy": 1730,
      "sell": 1700,
      "spbuy": 1770.03,
      "spsell": 1700.97
    },
    "HKD": {
      "currency": "HKD",
      "base": 188.72,
      "buy": 188.5,
      "sell": 187,
      "spbuy": 192.43,
      "spsell": 185.01
    },
    "TWD": {
      "currency": "TWD",
      "base": 46.94,
      "buy": 45.5,
      "sell": 44.9,
      "spbuy": 53.08,
      "spsell": 42.25
    },
    "SGD": {
      "currency": "SGD",
      "base": 1160.59,
      "buy": 1155,
      "sell": 1150,
      "spbuy": 1183.68,
      "spsell": 1137.5
    },
    "THB": {
      "currency": "THB",
      "base": 45.92,
      "buy": 47.5,
      "sell": 45.6,
      "spbuy": 48.21,
      "spsell": 43.17
    },
    "PHP": {
      "currency": "PHP",
      "base": 24.6,
      "buy": 24.8,
      "sell": 24,
      "spbuy": 27.06,
      "spsell": 22.59
    },
    "MYR": {
      "currency": "MYR",
      "base": 373.54,
      "buy": 370,
      "sell": 363,
      "spbuy": 401.18,
      "spsell": 345.9
    },
    "IDR": {
      "currency": "IDR",
      "base": 8.62,
      "buy": 9.5,
      "sell": 8.3,
      "spbuy": 9.48,
      "spsell": 7.76
    },
    "VND": {
      "currency": "VND",
      "base": 5.61,
      "buy": 5.8,
      "sell": 5.5,
      "spbuy": 6.27,
      "spsell": 4.95
    },
    "AUD": {
      "currency": "AUD",
      "base": 1058.25,
      "buy": 1055,
      "sell": 1045,
      "spbuy": 1079.09,
      "spsell": 1037.41
    },
    "GBP": {
      "currency": "GBP",
      "base": 1996.57,
      "buy": 1985,
      "sell": 1966,
      "spbuy": 2035.9,
      "spsell": 1957.24
    },
    "RUB": {
      "currency": "RUB",
      "base": 19.69,
      "buy": 19.5,
      "sell": 16,
      "spbuy": 21.56,
      "spsell": 16.25
    },
    "CHF": {
      "currency": "CHF",
      "base": 1893.29,
      "buy": 1895,
      "sell": 1860,
      "spbuy": 1930.58,
      "spsell": 1856
    },
    "CAD": {
      "currency": "CAD",
      "base": 1082,
      "buy": 1075,
      "sell": 1065,
      "spbuy": 1103.31,
      "spsell": 1060.69
    },
    "NZD": {
      "currency": "NZD",
      "base": 872.77,
      "buy": 880,
      "sell": 848,
      "spbuy": 889.96,
      "spsell": 855.58
    },
    "AED": {
      "currency": "AED",
      "base": 402.35,
      "buy": 424.47,
      "sell": 360,
      "spbuy": 424.47,
      "spsell": 374.59
    },
    "GFT": {
      "currency": "GFT",
      "base": 1,
      "buy": 1,
      "sell": 1,
      "spbuy": 1,
      "spsell": 1
    }
  }
}